sql_database_service/__init__.py
sql_database_service/database_service.py
sql_database_service/table_service.py
sql_database_service-0.0.12.dist-info/LICENSE
sql_database_service-0.0.12.dist-info/METADATA
sql_database_service-0.0.12.dist-info/WHEEL
sql_database_service-0.0.12.dist-info/top_level.txt
sql_database_service-0.0.12.dist-info/RECORD
