Metadata-Version: 2.1
Name: sql-database-service
Version: 0.0.12
Summary: This repo provides a library to do the basic CRUD operations in addition to grouping and sorting on an SQL database
Home-page: https://github.com/Quakingaspen-codehub/sql_database_service
Author: Quaking Aspen
Author-email: info@quakingaspen.net
License: MIT
Platform: UNKNOWN
Classifier: Programming Language :: Python :: 3
Classifier: License :: OSI Approved :: MIT License
Classifier: Operating System :: OS Independent
Requires-Python: >=3.6
License-File: LICENSE
